EC2Spawner/EC2Spawner.py
EC2Spawner/__init__.py
EC2Spawner/data/bootstrap.sh
jupyterhub_ec2spawner-0.24.dist-info/LICENSE
jupyterhub_ec2spawner-0.24.dist-info/METADATA
jupyterhub_ec2spawner-0.24.dist-info/WHEEL
jupyterhub_ec2spawner-0.24.dist-info/top_level.txt
jupyterhub_ec2spawner-0.24.dist-info/RECORD
